network_control/__init__.py
network_control/energies.py
network_control/metrics.py
network_control/plotting.py
network_control/utils.py
network_control-0.0.5.dist-info/LICENSE
network_control-0.0.5.dist-info/METADATA
network_control-0.0.5.dist-info/WHEEL
network_control-0.0.5.dist-info/top_level.txt
network_control-0.0.5.dist-info/RECORD
