Metadata-Version: 2.1
Name: network-control
Version: 0.0.5
Summary: Python implementation of concepts from network control theory
Home-page: https://github.com/BassettLab/control_package
Author: Jennifer Stiso, Linden Parkes and Jason Kim
Author-email: jeni.stiso@gmail.com, lindenmp@seas.upenn.edu, jinsu1@seas.upenn.edu
License: UNKNOWN
Project-URL: Bug Tracker, https://github.com/BassettLab/control_package/issues
Platform: UNKNOWN
Classifier: Programming Language :: Python :: 3
Classifier: License :: OSI Approved :: MIT License
Classifier: Operating System :: OS Independent
Requires-Python: >=3.6
License-File: LICENSE
Requires-Dist: numpy
Requires-Dist: scipy
